AUTHORS.rst
CONTRIBUTING.rst
HISTORY.rst
LICENSE
MANIFEST.in
README.rst
setup.cfg
setup.py
docs/Makefile
docs/authors.rst
docs/conf.py
docs/contributing.rst
docs/history.rst
docs/index.rst
docs/installation.rst
docs/make.bat
docs/readme.rst
docs/usage.rst
tests/__init__.py
tests/test_wetland.py
wetland/__init__.py
wetland/cli.py
wetland/wetland.py
wetland.egg-info/PKG-INFO
wetland.egg-info/SOURCES.txt
wetland.egg-info/dependency_links.txt
wetland.egg-info/entry_points.txt
wetland.egg-info/not-zip-safe
wetland.egg-info/requires.txt
wetland.egg-info/top_level.txt