Metadata-Version: 1.1
Name: wetland
Version: 0.1.0
Summary: Mapping surface water and wetland hydrological dynamics using Google Earth Engine
Home-page: https://github.com/giswqs/wetland
Author: Qiusheng Wu
Author-email: giswqs@gmail.com
License: MIT license
Keywords: wetland
Platform: UNKNOWN
Classifier: Development Status :: 2 - Pre-Alpha
Classifier: Intended Audience :: Developers
Classifier: License :: OSI Approved :: MIT License
Classifier: Natural Language :: English
Classifier: Programming Language :: Python :: 2
Classifier: Programming Language :: Python :: 2.7
Classifier: Programming Language :: Python :: 3
Classifier: Programming Language :: Python :: 3.4
Classifier: Programming Language :: Python :: 3.5
Classifier: Programming Language :: Python :: 3.6
Classifier: Programming Language :: Python :: 3.7
